
[
  {
    "id": 1,
    "title": "Betta Fish",
    "price": 11.99,
    "image": "/images/betta.jpg",
    "description": "small colorful betta fish."
  },
  {
    "id": 2,
    "title": "Blob Fish",
    "price": 40.99,
    "image": "/images/blobfish.jpg",
    "description": "ugly fish, but very rare."
  },
  {
    "id": 3,
    "title": "Catfish",
    "price": 30.99,
    "image": "/images/catfish.jpg",
    "description": "loves to eat scraps at the bottom of the water."
  },
  {
    "id": 4,
    "title": "Clownfish",
    "price": 28.99,
    "image": "/images/clownfish.webp",
    "description": "adorable small fish."
  },
  {
    "id": 5,
    "title": "Megalodon",
    "price": 999999.99,
    "image": "/images/megalodon.webp",
    "description": "massive prehistoric shark, super rare"
  },
  {
    "id": 6,
    "title": "Zooplankton",
    "price": 0.01,
    "image": "/images/plankton.jpg",
    "description": "tiny sea creature."
  },
  {
    "id": 7,
    "title": "Moray Eel",
    "price": 101.99,
    "image": "/images/moray.jpg",
    "description": "large dangerous eel."
  },
  {
    "id": 8,
    "title": "Anglerfish",
    "price": 300.49,
    "image": "/images/angler.png",
    "description": "hideous deep sea creature."
  },
  {
    "id": 9,
    "title": "Largemouth Bass",
    "price": 30.09,
    "image": "/images/Largemouth Bass.webp",
    "description": "common river fish."
  }
]